AUTHORS
INSTALL
LICENSE
MANIFEST.in
NOTICE
README
requirements.txt
setup.cfg
setup.py
contrib/example-project/QUICKSTART
contrib/example-project/__init__.py
contrib/example-project/manage.py
contrib/example-project/settings.py
contrib/example-project/urls.py
docs/Makefile
docs/conf.py
docs/configuration.rst
docs/faq.rst
docs/index.rst
docs/installation.rst
docs/introduction.rst
docs/make.bat
docs/usage.rst
src/django_postgresql_manager.egg-info/PKG-INFO
src/django_postgresql_manager.egg-info/SOURCES.txt
src/django_postgresql_manager.egg-info/dependency_links.txt
src/django_postgresql_manager.egg-info/top_level.txt
src/postgresql_manager/__init__.py
src/postgresql_manager/admin.py
src/postgresql_manager/forms.py
src/postgresql_manager/managers.py
src/postgresql_manager/models.py
src/postgresql_manager/settings.py
src/postgresql_manager/signal_cb.py
src/postgresql_manager/tests.py
src/postgresql_manager/utils.py